{
  "ProductName": "Engine Artwork",
  "DeveloperName": "Moenen",
  "ProjectType": 1,
  "MajorVersion": 0,
  "MinorVersion": 0,
  "PatchVersion": 1,
  "EngineBuildVersion": 16,
  "UseProceduralMap": false,
  "UseMapEditor": true,
  "UseLightingSystem": true,
  "ReadonlyMap": false,
  "AllowCheatCode": false,
  "AllowPause": true,
  "AllowQuitFromMenu": true,
  "AllowRestartFromMenu": true,
  "ScaleUiBasedOnMonitor": true,
  "ViewRatio": 2000,
  "DefaultViewHeight": 6656,
  "MinViewHeight": 4096,
  "MaxViewHeight": 15360,
  "LightMap_PixelStyle": false,
  "LightMap_SelfLerp": 0.88,
  "LightMap_SolidIlluminance": 1,
  "LightMap_AirIlluminanceDay": 0.95,
  "LightMap_AirIlluminanceNight": 0.3,
  "LightMap_BackgroundTint": 0.5,
  "LightMap_LevelIlluminateRemain": 0.3,
  "WorldBehindParallax": 1300,
  "WorldBehindAlpha": 64,
  "RequireFixScriptNamesWhenAnalyse": false,
  "LastOpenAtlasIndex": 1,
  "LastEdittingViewPos": {
    "x": 0,
    "y": 0,
    "z": 0
  },
  "LastEdittingViewHeight": -1
}